logicblocks/event/persistence/__init__.py
logicblocks/event/persistence/converter.py
logicblocks/event/persistence/memory/__init__.py
logicblocks/event/persistence/memory/converters/__init__.py
logicblocks/event/persistence/memory/converters/clause.py
logicblocks/event/persistence/memory/converters/function.py
logicblocks/event/persistence/memory/converters/helpers.py
logicblocks/event/persistence/memory/converters/query.py
logicblocks/event/persistence/memory/converters/types.py
logicblocks/event/persistence/postgres/__init__.py
logicblocks/event/persistence/postgres/converters/__init__.py
logicblocks/event/persistence/postgres/converters/appliers.py
logicblocks/event/persistence/postgres/converters/clause.py
logicblocks/event/persistence/postgres/converters/function.py
logicblocks/event/persistence/postgres/converters/helpers.py
logicblocks/event/persistence/postgres/converters/query.py
logicblocks/event/persistence/postgres/converters/types.py
logicblocks/event/persistence/postgres/query.py
logicblocks/event/persistence/postgres/settings.py
logicblocks/event/persistence/postgres/types.py
logicblocks/event/persistence/py.typed
logicblocks/event/processing/NOTES.md
logicblocks/event/processing/__init__.py
logicblocks/event/processing/broker/__init__.py
logicblocks/event/processing/broker/base.py
logicblocks/event/processing/broker/factories.py
logicblocks/event/processing/broker/logger.py
logicblocks/event/processing/broker/strategies/__init__.py
logicblocks/event/processing/broker/strategies/distributed/__init__.py
logicblocks/event/processing/broker/strategies/distributed/broker.py
logicblocks/event/processing/broker/strategies/distributed/builder.py
logicblocks/event/processing/broker/strategies/distributed/coordinator.py
logicblocks/event/processing/broker/strategies/distributed/difference.py
logicblocks/event/processing/broker/strategies/distributed/factories.py
logicblocks/event/processing/broker/strategies/distributed/observer.py
logicblocks_event_store-0.1.9.dist-info/LICENSE.md
logicblocks_event_store-0.1.9.dist-info/METADATA
logicblocks_event_store-0.1.9.dist-info/WHEEL
logicblocks_event_store-0.1.9.dist-info/RECORD
