Metadata-Version: 2.1
Name: logicblocks.event.store
Version: 0.1.9
Summary: Eventing infrastructure for event sourced architectures.
License: MIT
Author: Toby Clemson
Author-email: tobyclemson@gmail.com
Requires-Python: >=3.13,<4.0
Classifier: License :: OSI Approved :: MIT License
Classifier: Programming Language :: Python :: 3
Requires-Dist: aiologic (>=0.14.0,<0.15.0)
Requires-Dist: psycopg[binary,pool] (>=3.2.3,<4.0.0)
Requires-Dist: pyheck (>=0.1.5,<0.2.0)
Requires-Dist: rich (>=14.0.0,<15.0.0)
Requires-Dist: structlog (>=25.1.0,<26.0.0)
Requires-Dist: uvloop (>=0.21.0,<0.22.0)
